cardiopy/__init__.py
cardiopy/ekg.py
cardiopy-1.0.0.dist-info/LICENSE
cardiopy-1.0.0.dist-info/METADATA
cardiopy-1.0.0.dist-info/WHEEL
cardiopy-1.0.0.dist-info/top_level.txt
cardiopy-1.0.0.dist-info/RECORD
