Metadata-Version: 2.1
Name: cardiopy
Version: 1.0.0
Summary: Analysis package for single-lead clinical EKG data
Home-page: https://github.com/CardioPy/CardioPy
Author: Jackie Gottshall
Author-email: jackie.gottshall@gmail.com
License: UNKNOWN
Platform: UNKNOWN
Classifier: Programming Language :: Python :: 3
Classifier: License :: OSI Approved :: BSD License
Classifier: Operating System :: OS Independent
Classifier: Intended Audience :: Science/Research
Classifier: Topic :: Scientific/Engineering :: Medical Science Apps.
Requires-Python: >=3.6
Requires-Dist: datetime
Requires-Dist: matplotlib
Requires-Dist: pandas
Requires-Dist: scipy
Requires-Dist: statistics
Requires-Dist: mne
Requires-Dist: numpy
Requires-Dist: biosignalsnotebooks
